fastapi2postman.py
fastapi2postman-0.1.2.dist-info/LICENSE
fastapi2postman-0.1.2.dist-info/METADATA
fastapi2postman-0.1.2.dist-info/WHEEL
fastapi2postman-0.1.2.dist-info/entry_points.txt
fastapi2postman-0.1.2.dist-info/top_level.txt
fastapi2postman-0.1.2.dist-info/RECORD
